Metadata-Version: 1.1
Name: django-webapp
Version: 1.0.0
Summary: Integrate a front-end webapp and build process into Django and include a new runwebapp command.
Home-page: https://github.com/mvx24/django-webapp
Author: mvx24
Author-email: cram2400@gmail.com
License: MIT
Keywords: webapp django html5 front-end integrated
Platform: UNKNOWN
Classifier: Development Status :: 5 - Production/Stable
Classifier: Environment :: Console
Classifier: Framework :: Django
Classifier: License :: OSI Approved :: MIT License
Classifier: Operating System :: MacOS :: MacOS X
Classifier: Operating System :: POSIX
Classifier: Operating System :: Unix
Classifier: Programming Language :: Python :: 2.7
Classifier: Programming Language :: Python :: 2 :: Only
Classifier: Topic :: System :: Systems Administration
